{
    "display": {
        "icon": {
            "item": "alexscaves:gingerbread_crumbs"
        },
        "title": {
            "translate": "advancements.alexscaves.gingerbread_crumbs.title"
        },
        "description": {
            "translate": "advancements.alexscaves.gingerbread_crumbs.desc"
        }
    },
    "parent": "alexscaves:alexscaves/gingerbread_town",
    "criteria": {
        "crumbs": {
            "trigger": "minecraft:inventory_changed",
            "conditions": {
                "items": [
                    {
                        "items": ["alexscaves:gingerbread_crumbs"]
                    }
                ]
            }
        }
    }
}